terracodec/__init__.py
terracodec-0.1.0.dist-info/METADATA
terracodec-0.1.0.dist-info/WHEEL
terracodec-0.1.0.dist-info/top_level.txt
terracodec-0.1.0.dist-info/RECORD
