Metadata-Version: 2.4
Name: terracodec
Version: 0.1.0
Summary: Learned compression models for multispectral and multitemporal Earth Observation data.
Author-email: Julen Costa Watanabe <julen.costa@gmail.com>, Isabelle Wittmann <isabelle.wittmann1@ibm.com>, Benedikt Blumenstiel <benedikt.blumenstiel@ibm.com>
License-Expression: Apache-2.0
Project-URL: Homepage, https://github.com/IBM/terracodec
Project-URL: Repository, https://github.com/IBM/terracodec
Project-URL: Issues, https://github.com/IBM/terracodec/issues
Keywords: earth-observation,compression,deep-learning
Classifier: Programming Language :: Python :: 3.10
Classifier: Programming Language :: Python :: 3.11
Classifier: Programming Language :: Python :: 3.12
Classifier: Programming Language :: Python :: 3.13
Requires-Python: >=3.10
Requires-Dist: torch>=2.0.0
Requires-Dist: torchvision
Requires-Dist: terratorch>=1.0
Requires-Dist: huggingface-hub
